midd/__init__.py
midd/conversion.py
midd/main.py
midd/reporting.py
midd-1.1.2.dist-info/LICENSE
midd-1.1.2.dist-info/METADATA
midd-1.1.2.dist-info/WHEEL
midd-1.1.2.dist-info/entry_points.txt
midd-1.1.2.dist-info/top_level.txt
midd-1.1.2.dist-info/RECORD
