Metadata-Version: 2.1
Name: midd
Version: 1.1.2
Summary: The magic image duplicate detector works as its name suggests: it shows you potential duplicates of your images.
Home-page: https://github.com/renatoliveira/midd
Author: Renato Oliveira
Author-email: renatoliveira@pm.me
License: UNKNOWN
Platform: UNKNOWN
Classifier: Topic :: Scientific/Engineering :: Image Processing
Classifier: Topic :: Scientific/Engineering :: Image Recognition
Requires-Python: >=3.6
Requires-Dist: Pillow (==8.1.0)
Requires-Dist: click (>=6)
Requires-Dist: tqdm (==4.56.0)
